LICENSE
README.md
setup.py
example/__init__.py
example/models.py
nebula_carina/__init__.py
nebula_carina/apps.py
nebula_carina/settings.py
nebula_carina.egg-info/PKG-INFO
nebula_carina.egg-info/SOURCES.txt
nebula_carina.egg-info/dependency_links.txt
nebula_carina.egg-info/requires.txt
nebula_carina.egg-info/top_level.txt
nebula_carina/management/__init__.py
nebula_carina/management/commands/__init__.py
nebula_carina/management/commands/nebulamigrate.py
nebula_carina/models/__init__.py
nebula_carina/models/abstract.py
nebula_carina/models/errors.py
nebula_carina/models/fields.py
nebula_carina/models/managers.py
nebula_carina/models/migrations.py
nebula_carina/models/model_builder.py
nebula_carina/models/models.py
nebula_carina/models/query/__init__.py
nebula_carina/ngql/__init__.py
nebula_carina/ngql/errors.py
nebula_carina/ngql/connection/__init__.py
nebula_carina/ngql/connection/connection.py
nebula_carina/ngql/query/__init__.py
nebula_carina/ngql/query/conditions.py
nebula_carina/ngql/query/match.py
nebula_carina/ngql/record/__init__.py
nebula_carina/ngql/record/edge.py
nebula_carina/ngql/record/vertex.py
nebula_carina/ngql/schema/__init__.py
nebula_carina/ngql/schema/data_types.py
nebula_carina/ngql/schema/schema.py
nebula_carina/ngql/schema/space.py
nebula_carina/ngql/statements/__init__.py
nebula_carina/ngql/statements/clauses.py
nebula_carina/ngql/statements/core.py
nebula_carina/ngql/statements/edge.py
nebula_carina/ngql/statements/schema.py
nebula_carina/utils/__init__.py
nebula_carina/utils/utils.py
tests/__init__.py
tests/base.py
tests/test_ngql_record.py
tests/test_ngql_schema.py
tests/test_ngql_space.py