Metadata-Version: 2.1
Name: nebula-carina
Version: 0.3.1
Summary: Nebula Database Modeling powered by Pydantic and Nebula Python.
Home-page: https://github.com/SwordElucidator/nebula-carina
Author: Sword Elucidator
Author-email: nagisa940216@gmail.com
License: MIT Licence
Requires-Python: >=3.10
License-File: LICENSE
